{
  "kind": "collectionType",
  "collectionName": "use_case_articles",
  "info": {
    "singularName": "use-case-article",
    "pluralName": "use-case-articles",
    "displayName": "Use Case Article",
    "description": ""
  },
  "options": {
    "draftAndPublish": true
  },
  "pluginOptions": {},
  "attributes": {
    "title": {
      "type": "string",
      "required": true
    },
    "introVideoURL": {
      "type": "string",
      "required": true
    },
    "mainLink": {
      "type": "component",
      "repeatable": false,
      "component": "general.hyperlink"
    },
    "whitePaperLink": {
      "type": "component",
      "repeatable": false,
      "component": "general.hubspot-link",
      "required": true
    },
    "section1": {
      "type": "component",
      "repeatable": false,
      "component": "use-case-section.use-case-section1"
    },
    "section2": {
      "type": "component",
      "repeatable": false,
      "component": "use-case-section.use-case-section2",
      "required": true
    }
  }
}
